doc_layout_parser/__init__.py
doc_layout_parser/application/__init__.py
doc_layout_parser/application/document_parser.py
doc_layout_parser/application/document_parser_exceptions.py
doc_layout_parser/domain/__init__.py
doc_layout_parser/domain/base_document_parser.py
doc_layout_parser/domain/block.py
doc_layout_parser/domain/bounding_box.py
doc_layout_parser/domain/document.py
doc_layout_parser/domain/line.py
doc_layout_parser/domain/page.py
doc_layout_parser/domain/word.py
doc_layout_parser/infrastructure/__init__.py
doc_layout_parser/infrastructure/image_parser.py
doc_layout_parser/infrastructure/microsoft_word_parser.py
doc_layout_parser/infrastructure/pdf_parser.py
doc_layout_parser-2.5.6.dist-info/WHEEL
doc_layout_parser-2.5.6.dist-info/METADATA
doc_layout_parser-2.5.6.dist-info/RECORD
