Metadata-Version: 2.3
Name: doc-layout-parser
Version: 2.5.6
Summary: Пакет для разбивки различных документов (docx, pdf, изображения) на страницы, блоки, строки и слова
Author: Aksenov Mikhail
Requires-Dist: lxml>=6.0.2
Requires-Dist: pydantic>=2.0,<3.0
Requires-Dist: pymupdf>=1.26.7
Requires-Dist: pytesseract>=0.3.13
Requires-Python: >=3.10
